git_sci-0.0.1.dist-info/licenses/LICENSE
science/__init__.py
science/example.py
git_sci-0.0.1.dist-info/METADATA
git_sci-0.0.1.dist-info/WHEEL
git_sci-0.0.1.dist-info/top_level.txt
git_sci-0.0.1.dist-info/RECORD
