Metadata-Version: 2.4
Name: git-sci
Version: 0.0.1
Summary: A package for science
Author-email: Belinda Mo <justanexperimentpark@gmail.com>
License-Expression: MIT
Project-URL: Homepage, https://github.com/pypa/sampleproject
Project-URL: Issues, https://github.com/pypa/sampleproject/issues
Classifier: Programming Language :: Python :: 3
Classifier: Operating System :: OS Independent
Requires-Python: >=3.11
License-File: LICENSE
Dynamic: license-file
